setup.py
django_rawinclude.egg-info/PKG-INFO
django_rawinclude.egg-info/SOURCES.txt
django_rawinclude.egg-info/dependency_links.txt
django_rawinclude.egg-info/requires.txt
django_rawinclude.egg-info/top_level.txt
rawinclude/__init__.py
rawinclude/base.py
rawinclude/models.py
rawinclude/settings.py
rawinclude/tests.py
rawinclude/templatetags/__init__.py
rawinclude/templatetags/rawinclude.py