Metadata-Version: 1.1
Name: django-rawinclude
Version: 0.1
Summary: Small module for django that gives the ease of loading templates in raw.
Home-page: https://github.com/niwibe/django-rawinclude
Author: Andrei Antoukh
Author-email: niwi@niwi.be
License: BSD
Keywords: django,template,javascript
Platform: UNKNOWN
Classifier: Framework :: Django
Classifier: Intended Audience :: Developers
Classifier: License :: OSI Approved :: BSD License
Classifier: Operating System :: OS Independent
Classifier: Programming Language :: Python
Classifier: Topic :: Internet :: WWW/HTTP
Classifier: Programming Language :: Python :: 2.6
Classifier: Programming Language :: Python :: 2.7
